globsim/LazyLoader.py
globsim/__init__.py
globsim/__main__.py
globsim/_version.py
globsim/boundingbox.py
globsim/common_utils.py
globsim/constants.py
globsim/data_check.py
globsim/decorators.py
globsim/dreamit.py
globsim/era5_example.py
globsim/gap_checker.py
globsim/globsim_cli.py
globsim/globsim_convert.py
globsim/globsim_download.py
globsim/globsim_interpolate.py
globsim/globsim_main.py
globsim/globsim_scale.py
globsim/interp.py
globsim/jra_example.py
globsim/meteorology.py
globsim/nc_elements.py
globsim/redcapp.py
globsim/download/ERA5Edownload.py
globsim/download/ERA5download.py
globsim/download/GenericDownload.py
globsim/download/JRA3QJMAdownload.py
globsim/download/JRA3Q_dl.py
globsim/download/JRA3Q_helpers.py
globsim/download/JRA3Qdownload.py
globsim/download/JRAdownload.py
globsim/download/JraDownloadHandler.py
globsim/download/MERRAdownload.py
globsim/download/RDA.py
globsim/download/__init__.py
globsim/download/era5_monthly.py
globsim/download/era_helpers.py
globsim/download/jra_dict_formatters.py
globsim/download/rdams_client.py
globsim/interpolate/ERA5interpolate.py
globsim/interpolate/GenericInterpolate.py
globsim/interpolate/JRA3Qinterpolate.py
globsim/interpolate/JRAinterpolate.py
globsim/interpolate/MERRAinterpolate.py
globsim/interpolate/__init__.py
globsim/interpolate/create_grid_helper.py
globsim/scale/ERA5Escale.py
globsim/scale/ERA5scale.py
globsim/scale/GenericScale.py
globsim/scale/JRA3Qscale.py
globsim/scale/JRAscale.py
globsim/scale/MERRAscale.py
globsim/scale/TimeScaler.py
globsim/scale/__init__.py
globsim/scale/toposcale.py
globsim-4.4.1.dist-info/licenses/LICENSE
globsim-4.4.1.dist-info/METADATA
globsim-4.4.1.dist-info/WHEEL
globsim-4.4.1.dist-info/entry_points.txt
globsim-4.4.1.dist-info/top_level.txt
globsim-4.4.1.dist-info/RECORD
