Metadata-Version: 2.4
Name: globsim
Version: 4.4.1
Summary: Using global reanalysis data for local permafrost simulation
Home-page: https://github.com/geocryology/globsim
Author: Stephan Gruber
Author-email: stephan.gruber@carleton.ca
Classifier: Programming Language :: Python :: 2.7
Classifier: Programming Language :: Python :: 3
Classifier: License :: OSI Approved :: GNU General Public License v3 (GPLv3)
Classifier: Operating System :: POSIX :: Linux
Classifier: Topic :: Scientific/Engineering :: GIS
Classifier: Topic :: Scientific/Engineering :: Atmospheric Science
License-File: LICENSE
Requires-Dist: lxml
Requires-Dist: numpy>=2
Requires-Dist: pandas
Requires-Dist: netCDF4
Requires-Dist: scipy
Requires-Dist: dask
Requires-Dist: xarray
Requires-Dist: pydap>=3.4.1
Requires-Dist: tomlkit
Requires-Dist: cdsapi>=0.7.3
Requires-Dist: psutil
Requires-Dist: pysolar
Requires-Dist: pytz
Requires-Dist: cfgrib
Dynamic: author
Dynamic: author-email
Dynamic: classifier
Dynamic: description
Dynamic: description-content-type
Dynamic: home-page
Dynamic: license-file
Dynamic: requires-dist
Dynamic: summary
